<?xml version="1.0" encoding="utf-8" ?>
<characters>
  <character type="0" name="child_0" gender="0" age="7" cuteness="10" intelligence="3" artistry="3" athleticism="10" popularity="3" />
  <character type="0" name="child_1" gender="1" age="7" cuteness="10" intelligence="3" artistry="3" athleticism="10" popularity="3" />
  <character type="0" name="child_2" gender="0" age="7" cuteness="10" intelligence="3" artistry="3" athleticism="10" popularity="3" />
  <character type="0" name="child_3" gender="0" age="7" cuteness="10" intelligence="3" artistry="3" athleticism="10" popularity="3" />
  <character type="0" name="child_4" gender="0" age="7" cuteness="10" intelligence="3" artistry="3" athleticism="10" popularity="3" />
  <character type="0" name="child_5" gender="0" age="7" cuteness="10" intelligence="3" artistry="3" athleticism="10" popularity="3" />
  <character type="0" name="child_6" gender="0" age="7" cuteness="10" intelligence="3" artistry="3" athleticism="10" popularity="3" />
  <character type="0" name="child_7" gender="0" age="7" cuteness="10" intelligence="3" artistry="3" athleticism="10" popularity="3" />
  <character type="0" name="child_8" gender="0" age="7" cuteness="10" intelligence="3" artistry="3" athleticism="10" popularity="3" />
  <character type="1" name="Bob Bobs" gender="0" age="35" popularity="10" intelligence="3" love="3" />
  <character type="1" name="Jim Bobs" gender="0" age="35" popularity="10" intelligence="3" love="3" />
  <character type="1" name="Mike Samson" gender="0" age="35" popularity="10" intelligence="3" love="3" />
  <character type="1" name="Beth Beths" gender="1" age="35" popularity="10" intelligence="3" love="3" />
  <character type="1" name="Beth Botts" gender="1" age="35" popularity="10" intelligence="3" love="3" />
  <character type="2" name="Joe Cool" age="88" wisdom="10" insanity="3" money="50" />
  <character type="2" name="Joe Pool" age="88" wisdom="10" insanity="3" money="50" />
  <character type="2" name="Patrick Carney" age="88" wisdom="10" insanity="3" money="50" />
</characters>